MANIFEST.in
README.md
setup.py
univider/DemoClient.py
univider/__init__.py
univider/cacher.py
univider/encrypter.py
univider/esutil.py
univider/fetcher.py
univider/handler.py
univider/indexer.py
univider/logger.py
univider/render.js
univider/render.py
univider/reset.py
univider/settings.py
univider/storager.py
univider/subprocessor.py
univider/test_cacher.py
univider/test_compressor.py
univider/test_encoding.py
univider/test_hdfs.py
univider/test_hostname.py
univider/test_indexer.py
univider/test_log.py
univider/test_path.py
univider/test_redis.py
univider/test_render.py
univider/test_setting.py
univider/test_storager.py
univider/test_urllib2.py
univider.egg-info/PKG-INFO
univider.egg-info/SOURCES.txt
univider.egg-info/dependency_links.txt
univider.egg-info/entry_points.txt
univider.egg-info/requires.txt
univider.egg-info/top_level.txt
univider/gen-py/__init__.py
univider/gen-py/hbase/THBaseService.py
univider/gen-py/hbase/THBaseService4CMH.py
univider/gen-py/hbase/__init__.py
univider/gen-py/hbase/constants.py
univider/gen-py/hbase/ttypes.py