Metadata-Version: 1.0
Name: univider
Version: 0.0.1b0.dev59
Summary: yet another web spider interface
Home-page: http://puton.net
Author: taoyang,JavieYe
Author-email: ty@puton.net
License: Apache License, Version 2.0
Platform: UNKNOWN
